pybeep/__init__.py
pybeep/pybeep.py
pybeep/sounds.py
pybeep-0.0.4.dist-info/DESCRIPTION.rst
pybeep-0.0.4.dist-info/METADATA
pybeep-0.0.4.dist-info/metadata.json
pybeep-0.0.4.dist-info/RECORD
pybeep-0.0.4.dist-info/top_level.txt
pybeep-0.0.4.dist-info/WHEEL
