Metadata-Version: 2.0
Name: pybeep
Version: 0.0.4
Summary: Beeping in python
Home-page: https://github.com/kindlychung/pybeep
Author: Kaiyin Zhong
Author-email: kindlychung@gmail.com
License: UNKNOWN
Keywords: audio,beep
Platform: UNKNOWN
